moni/__init__.py
moni/main.py
moni-0.1.1.dist-info/LICENSE
moni-0.1.1.dist-info/METADATA
moni-0.1.1.dist-info/WHEEL
moni-0.1.1.dist-info/entry_points.txt
moni-0.1.1.dist-info/RECORD
